matej/__init__.py
matej/archive.py
matej/argparse.py
matej/callable.py
matej/cli.py
matej/collections.py
matej/colour.py
matej/config.py
matej/enum.py
matej/parallel.py
matej/re.py
matej/regedit.py
matej/string.py
matej/gui/__init__.py
matej/gui/pyqt.py
matej/gui/tkinter.py
matej/logging/__init__.py
matej/logging/filters.py
matej/logging/formatters.py
matej/logging/handlers.py
matej/logging/loggers.py
matej/math/__init__.py
matej/math/calculator.py
matej/nn/__init__.py
matej/nn/torch.py
matej/web/__init__.py
matej/web/cloud.py
matej/web/email.py
matej_libs-0.12.3.dist-info/METADATA
matej_libs-0.12.3.dist-info/WHEEL
matej_libs-0.12.3.dist-info/entry_points.txt
matej_libs-0.12.3.dist-info/top_level.txt
matej_libs-0.12.3.dist-info/RECORD
